[
 {
  "name": "Processor AMD Ryzen 7 8700F 4.1 - 5.0 GHz Socket AM5",
  "price": "Rp4.688.000",
  "rating": "N/A",
  "sold": "N/A"
 },
 {
  "name": "Processor AMD Ryzen 5 8400F 4.2 - 4.7 GHz Socket AM5",
  "price": "Rp3.090.000",
  "rating": "N/A",
  "sold": "N/A"
 },
 {
  "name": "Processor AMD Ryzen 5 8500G 3.5 - 5.0 GHz Socket AM5",
  "price": "Rp3.190.000",
  "rating": "N/A",
  "sold": "N/A"
 },
 {
  "name": "Processor AMD Ryzen 5 8600G 4.3 - 5.0 GHz Socket AM5",
  "price": "Rp4.010.000",
  "rating": "N/A",
  "sold": "N/A"
 },
 {
  "name": "Processor AMD Ryzen 7 8700G 4.2 - 5.1 GHz Socket AM5",
  "price": "Rp5.880.000",
  "rating": "N/A",
  "sold": "N/A"
 },
 {
  "name": "Processor AMD Ryzen 5 5600GT 3.6 - 4.6 GHz Socket AM4",
  "price": "Rp2.445.000",
  "rating": "N/A",
  "sold": "N/A"
 },
 {
  "name": "Processor AMD Ryzen 7 5700 3.7 - 4.6 GHz Socket AM4",
  "price": "Rp3.029.000",
  "rating": "N/A",
  "sold": "N/A"
 },
 {
  "name": "Processor AMD Ryzen 7 5700X3D 3.0 - 4.1 GHz Socket AM4",
  "price": "Rp4.385.000",
  "rating": "N/A",
  "sold": "N/A"
 },
 {
  "name": "Processor AMD Ryzen 7 5700X 3.7 - 4.6 GHz Socket AM4",
  "price": "Rp2.859.000",
  "rating": "N/A",
  "sold": "1 terjual"
 },
 {
  "name": "Processor AMD Ryzen 7 7700 3.8 - 5.3 GHz Socket AM5",
  "price": "Rp5.820.000",
  "rating": "N/A",
  "sold": "N/A"
 },
 {
  "name": "Processor AMD Ryzen 5 7600 3.8 - 5.1 GHz Socket AM5",
  "price": "Rp3.530.000",
  "rating": "N/A",
  "sold": "N/A"
 },
 {
  "name": "Processor AMD Ryzen 9 7950X3D 4.2 - 5.7 GHz Socket AM5",
  "price": "Rp11.250.000",
  "rating": "N/A",
  "sold": "N/A"
 },
 {
  "name": "Processor AMD Ryzen 9 7900X3D 4.4 - 5.6 GHz Socket AM5",
  "price": "Rp8.580.000",
  "rating": "N/A",
  "sold": "N/A"
 },
 {
  "name": "Processor AMD Ryzen 5 7600X 4.7 - 5.3 GHz Socket AM5",
  "price": "Rp3.955.000",
  "rating": "5.0",
  "sold": "1 terjual"
 },
 {
  "name": "Processor AMD Ryzen 7 7700X 4.5 - 5.4 GHz Socket AM5",
  "price": "Rp6.025.000",
  "rating": "5.0",
  "sold": "1 terjual"
 },
 {
  "name": "Processor AMD Bristol A8 9600 3.4GHz Socket AM4",
  "price": "Rp755.000",
  "rating": "5.0",
  "sold": "6 terjual"
 }
]