[
 {
  "name": "Motherboard Asrock B650M PG Lightning AM5 DDR5",
  "price": "Rp2.085.000",
  "rating": "N/A",
  "sold": "1 terjual"
 },
 {
  "name": "Motherboard Asrock A520M/ac AM4 DDR4",
  "price": "Rp1.021.000",
  "rating": "N/A",
  "sold": "2 terjual"
 },
 {
  "name": "Motherboard Asus PRIME B450M-A II - AM4",
  "price": "Rp1.078.000",
  "rating": "5.0",
  "sold": "5 terjual"
 },
 {
  "name": "Motherboard Asus  PRIME A520M-K - AM4",
  "price": "Rp938.000",
  "rating": "5.0",
  "sold": "17 terjual"
 },
 {
  "name": "Motherboard Asus PRIME B550M-K - AM4",
  "price": "Rp1.370.000",
  "rating": "5.0",
  "sold": "4 terjual"
 },
 {
  "name": "Motherboard Gigabyte B650M K DDR5 - AM5",
  "price": "Rp1.945.000",
  "rating": "5.0",
  "sold": "14 terjual"
 },
 {
  "name": "Asrock B650M PG Lightning WiFi AM5 DDR5",
  "price": "Rp2.362.000",
  "rating": "5.0",
  "sold": "11 terjual"
 },
 {
  "name": "Motherboard Asrock B550M WiFi SE - AMD AM4",
  "price": "Rp1.670.000",
  "rating": "5.0",
  "sold": "15 terjual"
 },
 {
  "name": "Motherboard Asrock B550M Pro SE - AMD AM4",
  "price": "Rp1.570.000",
  "rating": "5.0",
  "sold": "30+ terjual"
 },
 {
  "name": "Motherboard Asrock B550M-HVS SE - AMD AM4",
  "price": "Rp1.084.000",
  "rating": "4.9",
  "sold": "13 terjual"
 },
 {
  "name": "Motherboard Asrock A620M-HDV M.2 AMD Socket AM5",
  "price": "Rp1.543.000",
  "rating": "5.0",
  "sold": "17 terjual"
 },
 {
  "name": "Motherboard Asrock B550M Phantom Gaming 4 - AM4",
  "price": "Rp1.438.000",
  "rating": "5.0",
  "sold": "30+ terjual"
 },
 {
  "name": "Motherboard Gigabyte B550M DS3H - AM4",
  "price": "Rp1.435.000",
  "rating": "5.0",
  "sold": "100+ terjual"
 },
 {
  "name": "Motherboard Asrock A520M-HVS",
  "price": "Rp908.000",
  "rating": "4.9",
  "sold": "250+ terjual"
 },
 {
  "name": "Motherboard Asrock B550M-HDV - AMD AM4",
  "price": "Rp1.175.000",
  "rating": "4.9",
  "sold": "250+ terjual"
 },
 {
  "name": "Motherboard Asrock B550M Steel Legend - AMD AM4",
  "price": "Rp2.179.000",
  "rating": "5.0",
  "sold": "100+ terjual"
 },
 {
  "name": "Motherboard Asrock B550 PRO4 - AMD AM4",
  "price": "Rp1.750.000",
  "rating": "5.0",
  "sold": "28 terjual"
 },
 {
  "name": "Motherboard Asrock B450M Steel Legend AM4 Socket",
  "price": "Rp1.372.000",
  "rating": "5.0",
  "sold": "500+ terjual"
 },
 {
  "name": "Motherboard Asrock B450M-HDV",
  "price": "Rp902.000",
  "rating": "5.0",
  "sold": "250+ terjual"
 },
 {
  "name": "Motherboard Gigabyte B450M K - AM4",
  "price": "Rp924.000",
  "rating": "5.0",
  "sold": "100+ terjual"
 },
 {
  "name": "Asrock X670E Steel Legend AM5 DDR5",
  "price": "Rp5.490.000",
  "rating": "5.0",
  "sold": "6 terjual"
 },
 {
  "name": "Motherboard Asrock B550M PRO4 - AMD AM4",
  "price": "Rp1.570.000",
  "rating": "5.0",
  "sold": "250+ terjual"
 }
]